raintools_colors/__init__.py
raintools_colors/color.py
raintools_colors/raintoolscolors.py
raintools_colors/themes.py
raintools_colors/utils.py
raintools_colors-0.1.2.dist-info/LICENSE
raintools_colors-0.1.2.dist-info/METADATA
raintools_colors-0.1.2.dist-info/WHEEL
raintools_colors-0.1.2.dist-info/top_level.txt
raintools_colors-0.1.2.dist-info/RECORD
