Metadata-Version: 2.1
Name: raintools_colors
Version: 0.1.2
Summary: A versatile Python module for terminal color and style formatting, allowing easy customization of text appearance in command line applications.
Author: Plingenn
Author-email: raintool@engineer.com
Classifier: Programming Language :: Python :: 3
Classifier: Operating System :: OS Independent
Classifier: License :: OSI Approved :: MIT License
Classifier: Intended Audience :: Developers
Classifier: Natural Language :: English
Requires-Python: >=3.6
License-File: LICENSE
